Metadata-Version: 2.1
Name: certreader
Version: 0.1.1
Summary: Yet another x509 certificate parser.
Home-page: https://github.com/seocam/certreader
Author: Sergio Oliveira Campos
Author-email: seocam@redhat.com
License: UNKNOWN
Platform: UNKNOWN
Classifier: Programming Language :: Python :: 3
Classifier: License :: OSI Approved :: MIT License
Classifier: Operating System :: OS Independent
Requires-Python: >=3.6
